Metadata-Version: 2.4
Name: python-sql
Version: 1.6.0
Summary: Library to write SQL queries
Home-page: https://pypi.org/project/python-sql/
Download-URL: https://downloads.tryton.org/python-sql/
Author: Tryton
Author-email: foundation@tryton.org
License: BSD
Project-URL: Bug Tracker, https://bugs.tryton.org/python-sql
Project-URL: Forum, https://discuss.tryton.org/tags/python-sql
Project-URL: Source Code, https://code.tryton.org/python-sql
Keywords: SQL database query
Classifier: Development Status :: 5 - Production/Stable
Classifier: Intended Audience :: Developers
Classifier: License :: OSI Approved :: BSD License
Classifier: Operating System :: OS Independent
Classifier: Programming Language :: Python :: 3
Classifier: Programming Language :: Python :: 3.5
Classifier: Programming Language :: Python :: 3.6
Classifier: Programming Language :: Python :: 3.7
Classifier: Programming Language :: Python :: 3.8
Classifier: Programming Language :: Python :: 3.9
Classifier: Programming Language :: Python :: 3.10
Classifier: Programming Language :: Python :: 3.11
Classifier: Programming Language :: Python :: 3.12
Classifier: Programming Language :: Python :: 3.13
Classifier: Topic :: Database
Classifier: Topic :: Software Development :: Libraries :: Python Modules
Requires-Python: >=3.5
Dynamic: author
Dynamic: author-email
Dynamic: classifier
Dynamic: description
Dynamic: download-url
Dynamic: home-page
Dynamic: keywords
Dynamic: license
Dynamic: project-url
Dynamic: requires-python
Dynamic: summary
